wikiclass/__init__.py
wikiclass/about.py
wikiclass/assessments.py
wikiclass/wikiclass.py
wikiclass/extractors/__init__.py
wikiclass/extractors/enwiki.py
wikiclass/extractors/extractor.py
wikiclass/extractors/frwiki.py
wikiclass/extractors/ruwiki.py
wikiclass/extractors/tests/__init__.py
wikiclass/extractors/tests/test_enwiki.py
wikiclass/extractors/tests/test_extractor.py
wikiclass/extractors/tests/test_frwiki.py
wikiclass/extractors/tests/test_ruwiki.py
wikiclass/feature_lists/__init__.py
wikiclass/feature_lists/enwiki.py
wikiclass/feature_lists/frwiki.py
wikiclass/feature_lists/ruwiki.py
wikiclass/feature_lists/wikipedia.py
wikiclass/feature_lists/tests/__init__.py
wikiclass/feature_lists/tests/test_enwiki.py
wikiclass/feature_lists/tests/test_frwiki.py
wikiclass/features/__init__.py
wikiclass/features/extractor.py
wikiclass/features/meta.py
wikiclass/features/revision.py
wikiclass/features/wikitext_and_infonoise.py
wikiclass/features/metrics/__init__.py
wikiclass/features/metrics/infonoise.py
wikiclass/features/metrics/wikitext.py
wikiclass/features/tests/__init__.py
wikiclass/features/tests/test_meta.py
wikiclass/languages/__init__.py
wikiclass/languages/english.py
wikiclass/languages/language.py
wikiclass/models/__init__.py
wikiclass/models/model.py
wikiclass/models/rf_text.py
wikiclass/scorer_models/__init__.py
wikiclass/scorer_models/enwiki.py
wikiclass/util/__init__.py
wikiclass/util/autovivifying.py
wikiclass/utilities/__init__.py
wikiclass/utilities/extract_features.py
wikiclass/utilities/extract_from_text.py
wikiclass/utilities/extract_labelings.py
wikiclass/utilities/extract_scores.py
wikiclass/utilities/extract_text.py
wikiclass/utilities/fetch_text.py
wikiclass/utilities/score.py
wikiclass-0.3.2.dist-info/DESCRIPTION.rst
wikiclass-0.3.2.dist-info/METADATA
wikiclass-0.3.2.dist-info/RECORD
wikiclass-0.3.2.dist-info/WHEEL
wikiclass-0.3.2.dist-info/entry_points.txt
wikiclass-0.3.2.dist-info/metadata.json
wikiclass-0.3.2.dist-info/top_level.txt
