Metadata-Version: 2.0
Name: wikiclass
Version: 0.3.2
Summary: A library for performing automatic detection of assessment classes of Wikipedia articles.
Home-page: https://github.com/wiki-ai/editquality
Author: Aaron Halfaker / Morten Warncke-Wang
Author-email: ahalfaker@wikimedia.org
License: MIT
Platform: UNKNOWN
Classifier: Development Status :: 4 - Beta
Classifier: Topic :: Software Development :: Libraries :: Python Modules
Classifier: Programming Language :: Python
Classifier: Programming Language :: Python :: 3
Classifier: Intended Audience :: Developers
Classifier: License :: OSI Approved :: MIT License
Classifier: Operating System :: OS Independent
Classifier: Topic :: Text Processing :: Linguistic
Classifier: Topic :: Text Processing :: General
Classifier: Topic :: Utilities
Classifier: Topic :: Scientific/Engineering
Requires-Dist: revscoring (>=1.3.3,<1.3.999)
Requires-Dist: mwapi
Requires-Dist: mwreverts
Requires-Dist: mwtypes (>=0.2.0)
Requires-Dist: mwxml
